LICENSE
echo1_image_slicer/__init__.py
echo1_image_slicer/echo1_image_slicer.py
echo1_image_slicer/helpers/sahi.py
echo1_image_slicer-0.1.8.dist-info/entry_points.txt
echo1_image_slicer-0.1.8.dist-info/LICENSE
echo1_image_slicer-0.1.8.dist-info/WHEEL
echo1_image_slicer-0.1.8.dist-info/METADATA
echo1_image_slicer-0.1.8.dist-info/RECORD
