Metadata-Version: 2.1
Name: echo1-image-slicer
Version: 0.1.8
Summary: 
Home-page: https://github.com/e1-io/echo1-image-slicer
License: MIT
Author: Michael Mohamed
Author-email: michael.mohamed@echo1.io
Requires-Python: >=3.8,<4.0
Classifier: License :: OSI Approved :: MIT License
Classifier: Programming Language :: Python :: 3
Classifier: Programming Language :: Python :: 3.10
Classifier: Programming Language :: Python :: 3.8
Classifier: Programming Language :: Python :: 3.9
Requires-Dist: Pillow (>=9.0.1,<10.0.0)
Requires-Dist: loguru (>=0.6.0,<0.7.0)
Requires-Dist: numpy (>=1.22.2,<2.0.0)
Requires-Dist: requests (>=2.28.1,<3.0.0)
Project-URL: Repository, https://github.com/e1-io/echo1-image-slicerr
